marauder_sql/__init__.py
marauder_sql/connection.py
marauder_sql-0.1.0.dist-info/METADATA
marauder_sql-0.1.0.dist-info/WHEEL
marauder_sql-0.1.0.dist-info/top_level.txt
marauder_sql-0.1.0.dist-info/RECORD
