Metadata-Version: 2.4
Name: marauder-sql
Version: 0.1.0
Summary: A magical FastAPI utility package for PostgreSQL raw SQL operations
Home-page: https://github.com/justtil/marauder-sql
Author: Til Schwarze
Author-email: info@maraudersql.org
Keywords: fastapi,postgresql,database,sql,harry potter,marauder
Classifier: Programming Language :: Python :: 3
Classifier: Programming Language :: Python :: 3.8
Classifier: Programming Language :: Python :: 3.9
Classifier: Programming Language :: Python :: 3.10
Classifier: License :: OSI Approved :: MIT License
Classifier: Operating System :: OS Independent
Classifier: Framework :: FastAPI
Classifier: Topic :: Database :: Database Engines/Servers
Requires-Python: >=3.8
Requires-Dist: fastapi>=0.68.0
Requires-Dist: psycopg2-binary>=2.9.1
Requires-Dist: asyncpg>=0.24.0
Requires-Dist: pydantic>=1.8.2
Provides-Extra: dev
Requires-Dist: pytest>=6.2.5; extra == "dev"
Requires-Dist: black>=21.5b2; extra == "dev"
Requires-Dist: isort>=5.9.1; extra == "dev"
Requires-Dist: mypy>=0.812; extra == "dev"
Requires-Dist: flake8>=3.9.2; extra == "dev"
Provides-Extra: test
Requires-Dist: pytest>=6.2.5; extra == "test"
Requires-Dist: pytest-asyncio>=0.15.1; extra == "test"
Requires-Dist: pytest-cov>=2.12.1; extra == "test"
Dynamic: author
Dynamic: author-email
Dynamic: classifier
Dynamic: description-content-type
Dynamic: home-page
Dynamic: keywords
Dynamic: provides-extra
Dynamic: requires-dist
Dynamic: requires-python
Dynamic: summary
